Workbook

Sheet Premissas
B1: MODELO ECONÔMICO — RENATA BETTA
B2: Assessoria Completa com tráfego pago · 6 meses · criado 21/08/2026
B4: COMO USAR
B5: Edite SOMENTE as células amarelas desta aba. Todo o resto é fórmula e recalcula sozinho.
B6: Azul = valor digitado · Preto = fórmula · Verde = vem de outra aba
B7: ⚠ O faturamento realizado NÃO foi perguntado na call. A linha "receita hoje" é MODELO, não dado.
B9: FUNIL ATUAL DELA
B10: Leads por mês | C10: 100 | D10: [D] | E10: C-05: ~20/semana, "uns cem leads por mês"
B11: Conversão lead → consulta | C11: 0.275 | D11: [D] | E11: C-06: "dessas vinte, umas cinco, seis fecham"
B12: Conversão consulta → tratamento | C12: 0.55 | D12: [D] | E12: C-07: "converto uns cinquenta, sessenta"
B13: Preço da consulta | C13: 290 | D13: [D] | E13: C-02: porta de entrada PAGA
B14: Preço do tratamento | C14: 2500 | D14: [D] | E14: C-03: 4 encontros
B15: Encontros por tratamento | C15: 4 | D15: [D] | E15: C-03
B16: Duração do tratamento (meses) | C16: 2.5 | D16: [D] | E16: C-04
B18: CAPACIDADE DELA
B19: Atendimentos por dia | C19: 2.5 | D19: [D] | E19: C-32: "duas, três pessoas por dia"
B20: Dias úteis por mês | C20: 22 | D20: [M]
B22: MENTORIA EM GRUPO
B23: Ticket da mentoria | C23: 2500 | D23: [D] | E23: C-12: praticou 2.500, 3.000 e 4.000
B24: Margem de contribuição | C24: 0.9 | D24: [M] | E24: custo marginal ~zero; 10% p/ gateway e plataforma
B25: Margem do tratamento presencial | C25: 0.95 | D25: [M] | E25: custo variável mínimo
B27: BASE JÁ ATENDIDA
B28: Contatos na base | C28: 500 | D28: [H] | E28: bio: "+500 pessoas". NUNCA citada na call. VALIDAR
B30: NOSSO PREÇO E A VERBA DELA
B31: Honorário mensal (nosso) | C31: 4500 | D31: [M] | E31: Assessoria Completa, POLITICAS §5
B32: Meses de contrato | C32: 6 | D32: [M] | E32: 3 meses NÃO fecha o piso: exigiria R$ 5.000/mês
B33: Verba de mídia mensal (dela) | C33: 3000 | D33: [M] | E33: piso 2.000. Abaixo disso valida mensagem, não escala
B35: CENÁRIO ATIVO — mude aqui para ver os três
B36: Aumento do preço do tratamento (novo preço) | C36: 5000 | E36: conservador 3.500 · provável 5.000 · otimista 5.000
B37: Perda de volume esperada com o novo preço | C37: 0.4 | E37: conservador 20% · provável 40% · otimista 30%
B38: Conversão lead excedente → mentoria | C38: 0.075 | E38: n=0. conservador 5% · provável 7,5% · otimista 12,5%
B39: Conversão da base em 90 dias | C39: 0.02 | E39: conservador 1% · provável 2% · otimista 4%
B41: LEGENDA DE FONTE
B42: [D] dado dito por ela na call de 21/08 (ID na coluna E)
B43: [M] derivado ou premissa nossa, declarada
B44: [H] hipótese não validada — validar antes de usar

Sheet 1. O Teto
B1: O TETO — o funil entrega mais do que a agenda absorve
B3: A) SE A AGENDA FOSSE INFINITA
B4: Consultas por mês | C4: =Premissas!C10*Premissas!C11 -> 27.5 | F4: leads × conversão lead→consulta
B5: Tratamentos por mês | C5: =C4*Premissas!C12 -> 15.125 | F5: consultas × conversão consulta→tratamento
B6: Sessões que isso exigiria | C6: =C4+C5*Premissas!C15 -> 88 | F6: consultas + (tratamentos × 4 encontros ao longo da vida do tratamento)
B7: Receita teórica do funil | C7: =C4*Premissas!C13+C5*Premissas!C14 -> 45787.5 | F7: o que o funil produziria sem restrição de agenda
B9: B) O QUE A AGENDA COMPORTA
B10: Capacidade da agenda | C10: =Premissas!C19*Premissas!C20 -> 55 | F10: atendimentos/dia × dias úteis
B11: Sessões por tratamento fechado (consulta + encontros) | C11: =(1/Premissas!C12)+Premissas!C15 -> 5.8181818 | F11: cada tratamento fechado consome 1/0,55 consultas + 4 encontros
B12: Tratamentos/mês que a agenda comporta | C12: =C10/C11 -> 9.453125 | F12: satura a agenda
B13: Consultas/mês correspondentes | C13: =C12/Premissas!C12 -> 17.1875
B14: Leads consumidos | C14: =C13/Premissas!C11 -> 62.5
B15: LEADS SEM DESTINO | C15: =Premissas!C10-C14 -> 37.5 | F15: ⭐ o excedente que a mentoria absorve
B16: RECEITA ESTIMADA HOJE | C16: =C13*Premissas!C13+C12*Premissas!C14 -> 28617.188 | F16: ⚠ MODELO, não dado. Faturamento não foi perguntado
B18: RECEITA NÃO REALIZADA | C18: =C7-C16 -> 17170.312 | F18: é o custo da inação (Âncora 4)
B20: Você não bate a meta porque a demanda dá exatamente para ela. Você bate porque a agenda enche antes.

Sheet 2. Alavancas
B1: AS TRÊS ALAVANCAS
B3: ALAVANCA 1 — PREÇO do presencial (semana 2, custo zero, não depende de nós)
B4: Tratamentos hoje | C4: ='1. O Teto'!C12 -> 9.453125
B5: Novo preço | C5: =Premissas!C36 -> 5000
B6: Perda de volume | C6: =Premissas!C37 -> 0.4
B7: Tratamentos depois | C7: =C4*(1-C6) -> 5.671875
B8: Margem antes | C8: =C4*Premissas!C14*Premissas!C25 -> 22451.172
B9: Margem depois | C9: =C7*C5*Premissas!C25 -> 26941.406
B10: GANHO POR MÊS | C10: =C9-C8 -> 4490.2344 | F10: ⭐ o volume perdido é volume que ela não conseguia atender
B11: Agenda liberada (sessões/mês) | C11: =(C4-C7)*'1. O Teto'!C11 -> 22 | F11: ⭐ é o espaço onde o grupo cabe
B13: ALAVANCA 2 — MENTORIA absorve o excedente de leads
B14: Leads sem destino | C14: ='1. O Teto'!C15 -> 37.5
B15: Conversão lead → mentoria | C15: =Premissas!C38 -> 0.075 | F15: n=0 — não temos dado do funil digital de mentoria dela
B16: Vendas de mentoria por mês | C16: =C14*C15 -> 2.8125
B17: Margem por venda | C17: =Premissas!C23*Premissas!C24 -> 2250
B18: MARGEM POR MÊS | C18: =C16*C17 -> 6328.125
B20: ALAVANCA 3 — A BASE JÁ ATENDIDA (custo de mídia zero)
B21: Contatos na base | C21: =Premissas!C28 -> 500 | F21: ⚠ da bio, nunca confirmado. Validar contatos ativos reais
B22: Conversão em 90 dias | C22: =Premissas!C39 -> 0.02
B23: Vendas totais (uma vez só) | C23: =C21*C22 -> 10 | F23: alavanca de uma vez só: a base não se regenera nessa taxa
B24: MARGEM TOTAL | C24: =C23*C17 -> 22500

Sheet 3. Breakeven e Payback
B1: BREAKEVEN, FLUXO E PAYBACK
B3: BREAKEVEN — quantas vendas de mentoria por mês
B4: Desembolso mensal dela | C4: =Premissas!C31+Premissas!C33 -> 7500 | J4: honorário + verba de mídia
B5: Sem alavanca de preço | C5: =C4/'2. Alavancas'!C17 -> 3.3333333
B6: Custo residual com a alavanca de preço | C6: =MAX(0,C4-'2. Alavancas'!C10) -> 3009.7656
B7: COM alavanca de preço rodando | C7: =C6/'2. Alavancas'!C17 -> 1.3376736 | J7: ⭐ ela já fechou 16 vendas de mentoria, na unha, sem tráfego
B9: FLUXO MÊS A MÊS (cenário ativo na aba Premissas) | L9: RAMPAS (editáveis)
B10: Mês | C10: Desembolso | D10: Ganho de preço | E10: Mentoria | F10: Base | G10: Entrada | H10: Acum. saída | I10: Acum. entrada | J10: SALDO | L10: rampa mentoria | M10: rampa base
B11: 1 | C11: =$C$4 -> 7500 | D11: ='2. Alavancas'!$C$10 -> 4490.2344 | E11: ='2. Alavancas'!$C$18*L11 -> 0 | F11: ='2. Alavancas'!$C$24*M11 -> 4500 | G11: =D11+E11+F11 -> 8990.2344 | H11: =SUM($C$11:C11) -> 7500 | I11: =SUM($G$11:G11) -> 8990.2344 | J11: =I11-H11 -> 1490.2344 | L11: 0 | M11: 0.2 | N11: G1 gera dado, não lucro
B12: 2 | C12: =$C$4 -> 7500 | D12: ='2. Alavancas'!$C$10 -> 4490.2344 | E12: ='2. Alavancas'!$C$18*L12 -> 3164.0625 | F12: ='2. Alavancas'!$C$24*M12 -> 9000 | G12: =D12+E12+F12 -> 16654.297 | H12: =SUM($C$11:C12) -> 15000 | I12: =SUM($G$11:G12) -> 25644.531 | J12: =I12-H12 -> 10644.531 | L12: 0.5 | M12: 0.4
B13: 3 | C13: =$C$4 -> 7500 | D13: ='2. Alavancas'!$C$10 -> 4490.2344 | E13: ='2. Alavancas'!$C$18*L13 -> 6328.125 | F13: ='2. Alavancas'!$C$24*M13 -> 9000 | G13: =D13+E13+F13 -> 19818.359 | H13: =SUM($C$11:C13) -> 22500 | I13: =SUM($G$11:G13) -> 45462.891 | J13: =I13-H13 -> 22962.891 | L13: 1 | M13: 0.4 | N13: base concentrada nos 90 dias
B14: 4 | C14: =$C$4 -> 7500 | D14: ='2. Alavancas'!$C$10 -> 4490.2344 | E14: ='2. Alavancas'!$C$18*L14 -> 6328.125 | F14: ='2. Alavancas'!$C$24*M14 -> 0 | G14: =D14+E14+F14 -> 10818.359 | H14: =SUM($C$11:C14) -> 30000 | I14: =SUM($G$11:G14) -> 56281.25 | J14: =I14-H14 -> 26281.25 | L14: 1 | M14: 0
B15: 5 | C15: =$C$4 -> 7500 | D15: ='2. Alavancas'!$C$10 -> 4490.2344 | E15: ='2. Alavancas'!$C$18*L15 -> 6328.125 | F15: ='2. Alavancas'!$C$24*M15 -> 0 | G15: =D15+E15+F15 -> 10818.359 | H15: =SUM($C$11:C15) -> 37500 | I15: =SUM($G$11:G15) -> 67099.609 | J15: =I15-H15 -> 29599.609 | L15: 1 | M15: 0
B16: 6 | C16: =$C$4 -> 7500 | D16: ='2. Alavancas'!$C$10 -> 4490.2344 | E16: ='2. Alavancas'!$C$18*L16 -> 6328.125 | F16: ='2. Alavancas'!$C$24*M16 -> 0 | G16: =D16+E16+F16 -> 10818.359 | H16: =SUM($C$11:C16) -> 45000 | I16: =SUM($G$11:G16) -> 77917.969 | J16: =I16-H16 -> 32917.969 | L16: 1 | M16: 0
B18: PAYBACK (1º mês com saldo positivo) | C18: =IFERROR(MATCH(TRUE(),INDEX(J11:J16>0,0),0),"não ocorre em 6 meses") -> 1
B19: Saldo acumulado em 6 meses | C19: =J16 -> 32917.969
B20: ROI sobre o desembolso | C20: =IFERROR(J16/H16,0) -> 0.73151042
B22: ⚠ O cenário conservador precisa ser aceitável para ela. Se no pior caso o investimento machuca, a proposta não se faz.

Sheet 4. Nosso lado (INTERNO)
B1: ÂNCORA 7 — VIABILIDADE NOSSA
B2: ⚠ ESTA ABA NÃO VAI AO CLIENTE. Apagar antes de qualquer envio.
B4: ORÇAMENTO DE HORAS
B5: MÊS 1 — construção
B6: ICP + oferta + narrativa | C6: 8
B7: Roteiro da call de vendas | C7: 3
B8: Página | C8: 8
B9: Criativos iniciais (6-10) | C9: 6
B10: Estrutura de campanha + tracking | C10: 5
B11: Onboarding e calls | C11: 3
B12: Subtotal mês 1 | C12: =SUM(C6:C11) -> 33
B14: MESES 2-6 — operação (por mês)
B15: Gestão de campanha | C15: 5
B16: Criativos de reposição | C16: 3.5
B17: Call quinzenal + relatório | C17: 3
B18: Ajustes de copy e página | C18: 2
B19: Subtotal por mês | C19: =SUM(C15:C18) -> 13.5
B21: RESULTADO
B22: Horas totais do contrato | C22: =C12+C19*(Premissas!C32-1) -> 100.5
B23: Receita do contrato | C23: =Premissas!C31*Premissas!C32 -> 27000
B24: VALOR-HORA | C24: =C23/C22 -> 268.65672 | F24: piso R$ 250/h — POLITICAS §5
B25: Teto de horas para o piso | C25: =C23/250 -> 108
B26: FOLGA em horas | C26: =C25-C22 -> 7.5 | F26: ⚠ escopo travado é a condição de viabilidade
B27: Passa no piso? | C27: =IF(C24>=250,"SIM","NAO — REPROVA") -> SIM
B29: SENSIBILIDADE — e se estourar as horas?
B30: Horas extras | C30: Total | D30: Valor-hora | E30: Passa?
B31: 0 | C31: =$C$22+B31 -> 100.5 | D31: =$C$23/C31 -> 268.65672 | E31: =IF(D31>=250,"ok","FURA O PISO") -> ok
B32: 10 | C32: =$C$22+B32 -> 110.5 | D32: =$C$23/C32 -> 244.34389 | E32: =IF(D32>=250,"ok","FURA O PISO") -> FURA O PISO
B33: 20 | C33: =$C$22+B33 -> 120.5 | D33: =$C$23/C33 -> 224.06639 | E33: =IF(D33>=250,"ok","FURA O PISO") -> FURA O PISO
B34: 30 | C34: =$C$22+B34 -> 130.5 | D34: =$C$23/C34 -> 206.89655 | E34: =IF(D34>=250,"ok","FURA O PISO") -> FURA O PISO
B35: 40 | C35: =$C$22+B35 -> 140.5 | D35: =$C$23/C35 -> 192.17082 | E35: =IF(D35>=250,"ok","FURA O PISO") -> FURA O PISO
B37: 🔴 +10h já fura o piso. Uma página a mais, um VSL "rápido", um mês de conteúdo de bônus: qualquer um derruba a conta.
B38: 🔴 3 meses não fecha a R$ 4.500 (dá R$ 225/h). Se for 3 meses, o preço é R$ 5.000/mês. Teste mudando Premissas!C32.
B39: 🔴 Gate de capacidade da Nakielly NÃO rodado (POLITICAS §1: os dois gates, sempre).
